<?xml version="1.0" encoding="utf-8" ?><dwsync><file name="abbr.htm" server="kelvinwashingtonlive.com//" local="3373427280" remote="20553296464" /><file name="acronym.htm" server="kelvinwashingtonlive.com//" local="3373427280" remote="20553296464" /><file name="attributes.htm" server="kelvinwashingtonlive.com//" local="3373427280" remote="20553296464" /><file name="cite.htm" server="kelvinwashingtonlive.com//" local="3373427280" remote="20553296464" /><file name="del.htm" server="kelvinwashingtonlive.com//" local="3373427280" remote="20553296464" /><file name="editor_plugin.js" server="kelvinwashingtonlive.com//" local="3373427280" remote="20553296464" /><file name="editor_plugin_src.js" server="kelvinwashingtonlive.com//" local="3373427280" remote="20553296464" /><file name="ins.htm" server="kelvinwashingtonlive.com//" local="3373427280" remote="20553296464" /><file name="abbr.htm" server="livetmg.com//dm/clients/domdebeau/" local="3373427280" remote="11963952272" /><file name="acronym.htm" server="livetmg.com//dm/clients/domdebeau/" local="3373427280" remote="11963952272" /><file name="attributes.htm" server="livetmg.com//dm/clients/domdebeau/" local="3373427280" remote="11963952272" /><file name="cite.htm" server="livetmg.com//dm/clients/domdebeau/" local="3373427280" remote="11963952272" /><file name="del.htm" server="livetmg.com//dm/clients/domdebeau/" local="3373427280" remote="11963952272" /><file name="editor_plugin.js" server="livetmg.com//dm/clients/domdebeau/" local="3373427280" remote="11963952272" /><file name="editor_plugin_src.js" server="livetmg.com//dm/clients/domdebeau/" local="3373427280" remote="11963952272" /><file name="ins.htm" server="livetmg.com//dm/clients/domdebeau/" local="3373427280" remote="11963952272" /><file name="abbr.htm" server="dominiquedebeau.com//" local="3374694120" remote="11966868452" /><file name="acronym.htm" server="dominiquedebeau.com//" local="3374694120" remote="11966868452" /><file name="attributes.htm" server="dominiquedebeau.com//" local="3374694120" remote="11966868452" /><file name="cite.htm" server="dominiquedebeau.com//" local="3374694120" remote="11966868452" /><file name="del.htm" server="dominiquedebeau.com//" local="3374694120" remote="11966868512" /><file name="editor_plugin.js" server="dominiquedebeau.com//" local="3374694120" remote="11966868512" /><file name="editor_plugin_src.js" server="dominiquedebeau.com//" local="3374694120" remote="11966868512" /><file name="ins.htm" server="dominiquedebeau.com//" local="3374694120" remote="11966868512" /></dwsync>